cedict_utils/__init__.py
cedict_utils/cedict.py
cedict_utils/data/dump.dat
data/__init__.py
cedict_utils-0.0.13.dist-info/LICENSE.txt
cedict_utils-0.0.13.dist-info/METADATA
cedict_utils-0.0.13.dist-info/SOURCES.txt~
cedict_utils-0.0.13.dist-info/WHEEL
cedict_utils-0.0.13.dist-info/top_level.txt
cedict_utils-0.0.13.dist-info/RECORD
