Metadata-Version: 2.1
Name: cedict-utils
Version: 0.0.13
Summary: A Python parser for the CC-CEDICT Chinese-English dictionary
Home-page: https://github.com/marcanuy/cedict_utils
Author: Marcelo Canina
Author-email: me@marcanuy.com
License: MIT
Keywords: cedict dictionary chinese cc-cedict
Platform: UNKNOWN
Classifier: Development Status :: 4 - Beta
Classifier: Intended Audience :: Developers
Classifier: Topic :: Software Development :: Libraries
Classifier: License :: OSI Approved :: MIT License
Classifier: Programming Language :: Python :: 3
Classifier: Programming Language :: Python :: 3.5
Classifier: Programming Language :: Python :: 3.6
Classifier: Programming Language :: Python :: 3.7
Classifier: Programming Language :: Python :: 3.8
Provides-Extra: dev
Provides-Extra: test
